server_connector/__init__.py
server_connector/server.py
server_connector-0.0.1.dist-info/METADATA
server_connector-0.0.1.dist-info/WHEEL
server_connector-0.0.1.dist-info/top_level.txt
server_connector-0.0.1.dist-info/RECORD
