Metadata-Version: 2.1
Name: server-connector
Version: 0.0.1
Summary: A simple tool for developers that can perform operations on server with just a few line of codes.
Author: zadarmo
Author-email: wx01290804@163.com
License: MIT
Requires-Dist: paramiko
